slam/__init__.py
slam/cfn.py
slam/cli.py
slam/helpers.py
slam/plugins/__init__.py
slam/plugins/dynamodb.py
slam/plugins/wsgi.py
slam/templates/handler.py.template
slam/templates/slam.yaml
slam-0.6.1.dist-info/LICENSE
slam-0.6.1.dist-info/METADATA
slam-0.6.1.dist-info/WHEEL
slam-0.6.1.dist-info/entry_points.txt
slam-0.6.1.dist-info/top_level.txt
slam-0.6.1.dist-info/RECORD
