Metadata-Version: 2.1
Name: slam
Version: 0.6.1
Summary: Serverless application manager
Home-page: https://github.com/miguelgrinberg/slam/
Author: Miguel Grinberg
Author-email: miguelgrinberg50@gmail.com
License: MIT
Platform: any
Classifier: Environment :: Web Environment
Classifier: Intended Audience :: Developers
Classifier: License :: OSI Approved :: MIT License
Classifier: Operating System :: OS Independent
Classifier: Programming Language :: Python
Classifier: Programming Language :: Python :: 2
Classifier: Programming Language :: Python :: 3
Classifier: Topic :: Internet :: WWW/HTTP :: Dynamic Content
Classifier: Topic :: Software Development :: Libraries :: Python Modules
Requires-Dist: lambda-uploader
Requires-Dist: boto3
Requires-Dist: climax
Requires-Dist: merry
Requires-Dist: jinja2
Requires-Dist: pyyaml
Requires-Dist: virtualenv
